truefalsepython/__init__.py
truefalsepython/little.py
truefalsepython/logical.py
truefalsepython/other.py
truefalsepython/r_funcs.py
truefalsepython/useful_funcs.py
truefalsepython-0.2.0.dist-info/LICENSE
truefalsepython-0.2.0.dist-info/METADATA
truefalsepython-0.2.0.dist-info/WHEEL
truefalsepython-0.2.0.dist-info/top_level.txt
truefalsepython-0.2.0.dist-info/RECORD
