Metadata-Version: 2.1
Name: truefalsepython
Version: 0.2.0
Summary: PyPI package with some better syntax tools for python
Home-page: https://github.com/PasaOpasen/true-false-python
Author: Demetry Pascal
Author-email: qtckpuhdsa@gmail.com
Maintainer: ['Demetry Pascal']
License: UNKNOWN
Keywords: true,false,C,fun,funny,shit,r,tools
Platform: UNKNOWN
Classifier: Programming Language :: Python :: 3
Classifier: License :: OSI Approved :: MIT License
Classifier: Operating System :: OS Independent
Classifier: Topic :: Software Development :: Libraries :: Python Modules
License-File: LICENSE
Requires-Dist: numpy
